compute_oper1
