Metadata-Version: 2.1
Name: compute-oper1
Version: 0.0.1.3
Summary: Trial Basic calculator library, individual functions
Home-page: https://github.com/hongzhu6129/HidenFeatures
Author: Movin Fernandes
Author-email: movin.fernandes@hotmail.com
License: MIT
Keywords: basic,calculator
License-File: LICENCE.txt
